MANIFEST.in
README.rst
VERSION
changes.md
requirements.txt
setup.cfg
setup.py
alice/__init__.py
alice/checker_impl.py
alice/commons/__init__.py
alice/commons/base.py
alice/config/__init__.py
alice/config/config_provider.py
alice/config/message_template.py
alice/helper/__init__.py
alice/helper/api_manager.py
alice/helper/colors.py
alice/helper/common_utils.py
alice/helper/constants.py
alice/helper/file_utils.py
alice/helper/github_helper.py
alice/helper/log_utils.py
alice/helper/slack_helper.py
alice/helper/decorators/__init__.py
alice/helper/decorators/retry.py
alice/main/__init__.py
alice/main/actor.py
alice/main/checks.py
alice/main/runner.py
alice/tests/__init__.py
alice/tests/t1.py
alice/tests/test_m2/__init__.py
alice/tests/test_m2/test_p1/__init__.py
alice/tests/test_m2/test_p1/test_p2/__init__.py
alice/tests/test_m2/test_p1/test_p2/t_p2.py
alice/tests/tests_m1/__init__.py
alice_core.egg-info/PKG-INFO
alice_core.egg-info/SOURCES.txt
alice_core.egg-info/dependency_links.txt
alice_core.egg-info/not-zip-safe
alice_core.egg-info/requires.txt
alice_core.egg-info/top_level.txt
docs/checks.md
docs/extend_alice.md
docs/setup_config.md
docs/samples/config.json
docs/samples/config.yaml