Metadata-Version: 1.0
Name: alice-core
Version: 1.6.4
Summary: UNKNOWN
Home-page: https://github.com/moengage/alice
Author: Pooja Shah
Author-email: writeback2pooja@gmail.com
License: MIT
Platform: UNKNOWN
